ehelply_batcher/__init__.py
ehelply_batcher/abstract_batching_service.py
ehelply_batcher/abstract_timer_service.py
ehelply_batcher/batch.py
ehelply_batcher/tests/__init__.py
ehelply_batcher/tests/simulated_batching_service.py
ehelply_batcher/tests/simulated_timer_service.py
ehelply_batcher-1.5.0.dist-info/LICENSE
ehelply_batcher-1.5.0.dist-info/WHEEL
ehelply_batcher-1.5.0.dist-info/METADATA
ehelply_batcher-1.5.0.dist-info/RECORD
