Metadata-Version: 2.1
Name: ehelply-batcher
Version: 1.5.0
Summary: 
Home-page: https://ehelply.com
Author: Shawn Clake
Author-email: shawn.clake@gmail.com
Requires-Python: >=3.10
Classifier: Programming Language :: Python :: 3
Requires-Dist: ehelply-logger (>=0.0.8,<0.0.9)
Requires-Dist: pytest-asyncio (>=0.18.3,<0.19.0)
Requires-Dist: pytest-cov (>=3.0.0,<4.0.0)
Requires-Dist: typer (>=0.4.1,<0.5.0)
